{
  "total_sets": 991,
  "structure_keys": [
    "object",
    "has_more",
    "data"
  ],
  "sample_sets": [
    {
      "object": "set",
      "code": "tla",
      "name": "Avatar: The Last Airbender",
      "set_type": "expansion",
      "card_count": 110,
      "released_at": "2025-11-21",
      "keys": [
        "object",
        "id",
        "code",
        "mtgo_code",
        "arena_code",
        "tcgplayer_id",
        "name",
        "uri",
        "scryfall_uri",
        "search_uri",
        "released_at",
        "set_type",
        "card_count",
        "digital",
        "nonfoil_only",
        "foil_only",
        "icon_svg_uri"
      ]
    },
    {
      "object": "set",
      "code": "ftla",
      "name": "Avatar: The Last Airbender Front Cards",
      "set_type": "memorabilia",
      "card_count": 10,
      "released_at": "2025-11-21",
      "keys": [
        "object",
        "id",
        "code",
        "name",
        "uri",
        "scryfall_uri",
        "search_uri",
        "released_at",
        "set_type",
        "card_count",
        "parent_set_code",
        "digital",
        "nonfoil_only",
        "foil_only",
        "icon_svg_uri"
      ]
    },
    {
      "object": "set",
      "code": "tle",
      "name": "Avatar: The Last Airbender Eternal",
      "set_type": "expansion",
      "card_count": 101,
      "released_at": "2025-11-21",
      "keys": [
        "object",
        "id",
        "code",
        "mtgo_code",
        "arena_code",
        "tcgplayer_id",
        "name",
        "uri",
        "scryfall_uri",
        "search_uri",
        "released_at",
        "set_type",
        "card_count",
        "parent_set_code",
        "digital",
        "nonfoil_only",
        "foil_only",
        "icon_svg_uri"
      ]
    },
    {
      "object": "set",
      "code": "pspm",
      "name": "Marvel's Spider-Man Promos",
      "set_type": "promo",
      "card_count": 2,
      "released_at": "2025-09-26",
      "keys": [
        "object",
        "id",
        "code",
        "name",
        "uri",
        "scryfall_uri",
        "search_uri",
        "released_at",
        "set_type",
        "card_count",
        "parent_set_code",
        "digital",
        "nonfoil_only",
        "foil_only",
        "icon_svg_uri"
      ]
    },
    {
      "object": "set",
      "code": "tspm",
      "name": "Marvel's Spider-Man Tokens",
      "set_type": "token",
      "card_count": 0,
      "released_at": "2025-09-26",
      "keys": [
        "object",
        "id",
        "code",
        "name",
        "uri",
        "scryfall_uri",
        "search_uri",
        "released_at",
        "set_type",
        "card_count",
        "parent_set_code",
        "digital",
        "nonfoil_only",
        "foil_only",
        "icon_svg_uri"
      ]
    },
    {
      "object": "set",
      "code": "mar",
      "name": "Marvel Universe",
      "set_type": "expansion",
      "card_count": 0,
      "released_at": "2025-09-26",
      "keys": [
        "object",
        "id",
        "code",
        "name",
        "uri",
        "scryfall_uri",
        "search_uri",
        "released_at",
        "set_type",
        "card_count",
        "digital",
        "nonfoil_only",
        "foil_only",
        "icon_svg_uri"
      ]
    },
    {
      "object": "set",
      "code": "spm",
      "name": "Marvel's Spider-Man",
      "set_type": "expansion",
      "card_count": 99,
      "released_at": "2025-09-26",
      "keys": [
        "object",
        "id",
        "code",
        "tcgplayer_id",
        "name",
        "uri",
        "scryfall_uri",
        "search_uri",
        "released_at",
        "set_type",
        "card_count",
        "digital",
        "nonfoil_only",
        "foil_only",
        "icon_svg_uri"
      ]
    },
    {
      "object": "set",
      "code": "spe",
      "name": "Marvel's Spider-Man Eternal",
      "set_type": "expansion",
      "card_count": 26,
      "released_at": "2025-09-26",
      "keys": [
        "object",
        "id",
        "code",
        "name",
        "uri",
        "scryfall_uri",
        "search_uri",
        "released_at",
        "set_type",
        "card_count",
        "parent_set_code",
        "digital",
        "nonfoil_only",
        "foil_only",
        "icon_svg_uri"
      ]
    },
    {
      "object": "set",
      "code": "ph23",
      "name": "2023 Heroes of the Realm",
      "set_type": "funny",
      "card_count": 1,
      "released_at": "2025-08-24",
      "keys": [
        "object",
        "id",
        "code",
        "name",
        "uri",
        "scryfall_uri",
        "search_uri",
        "released_at",
        "set_type",
        "card_count",
        "digital",
        "nonfoil_only",
        "foil_only",
        "block_code",
        "block",
        "icon_svg_uri"
      ]
    },
    {
      "object": "set",
      "code": "aa2",
      "name": "Arena Anthology 2",
      "set_type": "expansion",
      "card_count": 25,
      "released_at": "2025-08-19",
      "keys": [
        "object",
        "id",
        "code",
        "name",
        "uri",
        "scryfall_uri",
        "search_uri",
        "released_at",
        "set_type",
        "card_count",
        "digital",
        "nonfoil_only",
        "foil_only",
        "icon_svg_uri"
      ]
    },
    {
      "object": "set",
      "code": "yeoe",
      "name": "Alchemy: Edge of Eternities",
      "set_type": "alchemy",
      "card_count": 30,
      "released_at": "2025-08-19",
      "keys": [
        "object",
        "id",
        "code",
        "name",
        "uri",
        "scryfall_uri",
        "search_uri",
        "released_at",
        "set_type",
        "card_count",
        "parent_set_code",
        "digital",
        "nonfoil_only",
        "foil_only",
        "icon_svg_uri"
      ]
    },
    {
      "object": "set",
      "code": "aa1",
      "name": "Arena Anthology 1",
      "set_type": "box",
      "card_count": 26,
      "released_at": "2025-08-19",
      "keys": [
        "object",
        "id",
        "code",
        "name",
        "uri",
        "scryfall_uri",
        "search_uri",
        "released_at",
        "set_type",
        "card_count",
        "digital",
        "nonfoil_only",
        "foil_only",
        "icon_svg_uri"
      ]
    },
    {
      "object": "set",
      "code": "aeoe",
      "name": "Edge of Eternities Art Series",
      "set_type": "memorabilia",
      "card_count": 54,
      "released_at": "2025-08-01",
      "keys": [
        "object",
        "id",
        "code",
        "name",
        "uri",
        "scryfall_uri",
        "search_uri",
        "released_at",
        "set_type",
        "card_count",
        "parent_set_code",
        "digital",
        "nonfoil_only",
        "foil_only",
        "icon_svg_uri"
      ]
    },
    {
      "object": "set",
      "code": "peoe",
      "name": "Edge of Eternities Promos",
      "set_type": "promo",
      "card_count": 160,
      "released_at": "2025-08-01",
      "keys": [
        "object",
        "id",
        "code",
        "name",
        "uri",
        "scryfall_uri",
        "search_uri",
        "released_at",
        "set_type",
        "card_count",
        "parent_set_code",
        "digital",
        "nonfoil_only",
        "foil_only",
        "icon_svg_uri"
      ]
    },
    {
      "object": "set",
      "code": "eoe",
      "name": "Edge of Eternities",
      "set_type": "expansion",
      "card_count": 399,
      "released_at": "2025-08-01",
      "keys": [
        "object",
        "id",
        "code",
        "mtgo_code",
        "arena_code",
        "tcgplayer_id",
        "name",
        "uri",
        "scryfall_uri",
        "search_uri",
        "released_at",
        "set_type",
        "card_count",
        "digital",
        "nonfoil_only",
        "foil_only",
        "icon_svg_uri"
      ]
    },
    {
      "object": "set",
      "code": "pbig",
      "name": "The Big Score Promos",
      "set_type": "promo",
      "card_count": 5,
      "released_at": "2025-08-01",
      "keys": [
        "object",
        "id",
        "code",
        "name",
        "uri",
        "scryfall_uri",
        "search_uri",
        "released_at",
        "set_type",
        "card_count",
        "parent_set_code",
        "digital",
        "nonfoil_only",
        "foil_only",
        "icon_svg_uri"
      ]
    },
    {
      "object": "set",
      "code": "eoc",
      "name": "Edge of Eternities Commander",
      "set_type": "commander",
      "card_count": 191,
      "released_at": "2025-08-01",
      "keys": [
        "object",
        "id",
        "code",
        "mtgo_code",
        "arena_code",
        "tcgplayer_id",
        "name",
        "uri",
        "scryfall_uri",
        "search_uri",
        "released_at",
        "set_type",
        "card_count",
        "parent_set_code",
        "digital",
        "nonfoil_only",
        "foil_only",
        "block_code",
        "block",
        "icon_svg_uri"
      ]
    },
    {
      "object": "set",
      "code": "teoc",
      "name": "Edge of Eternities Commander Tokens",
      "set_type": "token",
      "card_count": 16,
      "released_at": "2025-08-01",
      "keys": [
        "object",
        "id",
        "code",
        "mtgo_code",
        "arena_code",
        "name",
        "uri",
        "scryfall_uri",
        "search_uri",
        "released_at",
        "set_type",
        "card_count",
        "parent_set_code",
        "digital",
        "nonfoil_only",
        "foil_only",
        "icon_svg_uri"
      ]
    },
    {
      "object": "set",
      "code": "eos",
      "name": "Edge of Eternities: Stellar Sights",
      "set_type": "masterpiece",
      "card_count": 180,
      "released_at": "2025-08-01",
      "keys": [
        "object",
        "id",
        "code",
        "mtgo_code",
        "arena_code",
        "tcgplayer_id",
        "name",
        "uri",
        "scryfall_uri",
        "search_uri",
        "released_at",
        "set_type",
        "card_count",
        "parent_set_code",
        "digital",
        "nonfoil_only",
        "foil_only",
        "icon_svg_uri"
      ]
    },
    {
      "object": "set",
      "code": "teoe",
      "name": "Edge of Eternities Tokens",
      "set_type": "token",
      "card_count": 12,
      "released_at": "2025-08-01",
      "keys": [
        "object",
        "id",
        "code",
        "mtgo_code",
        "arena_code",
        "name",
        "uri",
        "scryfall_uri",
        "search_uri",
        "released_at",
        "set_type",
        "card_count",
        "parent_set_code",
        "digital",
        "nonfoil_only",
        "foil_only",
        "icon_svg_uri"
      ]
    }
  ],
  "set_types": [
    "masterpiece",
    "alchemy",
    "promo",
    "memorabilia",
    "funny",
    "box",
    "token",
    "expansion",
    "commander"
  ],
  "date_range": {
    "oldest": "2025-08-01",
    "newest": "2025-11-21"
  }
}